{
  "info": {
    "name": "SSO Service API",
    "_postman_id": "1c9d28e8-ec9d-4b50-8b1f-7f5c7f9a52a1",
    "description": "Auth and utility endpoints for sso-service.",
    "schema": "https://schema.getpostman.com/json/collection/v2.1.0/collection.json"
  },
  "variable": [
    { "key": "baseUrl", "value": "http://localhost:8090" },
    { "key": "email", "value": "user@example.com" },
    { "key": "password", "value": "Password@123" },
    { "key": "newPassword", "value": "NewPassword@123" },
    { "key": "deviceId", "value": "postman-device-1" },
    { "key": "verificationToken", "value": "paste_token_from_email_link" },
    { "key": "resetToken", "value": "paste_token_from_email_link" },
    { "key": "accessToken", "value": "" },
    { "key": "refreshToken", "value": "" }
  ],
  "item": [
    {
      "name": "Auth",
      "item": [
        {
          "name": "Register",
          "request": {
            "method": "POST",
            "header": [
              { "key": "Content-Type", "value": "application/json" }
            ],
            "body": {
              "mode": "raw",
              "raw": "{\n  \"email\": \"{{email}}\",\n  \"password\": \"{{password}}\"\n}"
            },
            "url": {
              "raw": "{{baseUrl}}/auth/register",
              "host": ["{{baseUrl}}"],
              "path": ["auth", "register"]
            }
          },
          "event": [
            {
              "listen": "test",
              "script": {
                "type": "text/javascript",
                "exec": [
                  "pm.test('Status is 200', function () { pm.response.to.have.status(200); });"
                ]
              }
            }
          ]
        },
        {
          "name": "Verify Email",
          "request": {
            "method": "GET",
            "url": {
              "raw": "{{baseUrl}}/auth/verify-email?token={{verificationToken}}",
              "host": ["{{baseUrl}}"],
              "path": ["auth", "verify-email"],
              "query": [
                { "key": "token", "value": "{{verificationToken}}" }
              ]
            }
          }
        },
        {
          "name": "Login",
          "request": {
            "method": "POST",
            "header": [
              { "key": "Content-Type", "value": "application/json" }
            ],
            "body": {
              "mode": "raw",
              "raw": "{\n  \"email\": \"{{email}}\",\n  \"password\": \"{{password}}\",\n  \"deviceId\": \"{{deviceId}}\"\n}"
            },
            "url": {
              "raw": "{{baseUrl}}/auth/login",
              "host": ["{{baseUrl}}"],
              "path": ["auth", "login"]
            }
          },
          "event": [
            {
              "listen": "test",
              "script": {
                "type": "text/javascript",
                "exec": [
                  "pm.test('Status is 200', function () { pm.response.to.have.status(200); });",
                  "const json = pm.response.json();",
                  "if (json.accessToken) pm.collectionVariables.set('accessToken', json.accessToken);",
                  "if (json.refreshToken) pm.collectionVariables.set('refreshToken', json.refreshToken);"
                ]
              }
            }
          ]
        },
        {
          "name": "Refresh",
          "request": {
            "method": "POST",
            "header": [
              { "key": "Content-Type", "value": "application/json" }
            ],
            "body": {
              "mode": "raw",
              "raw": "{\n  \"refreshToken\": \"{{refreshToken}}\",\n  \"deviceId\": \"{{deviceId}}\"\n}"
            },
            "url": {
              "raw": "{{baseUrl}}/auth/refresh",
              "host": ["{{baseUrl}}"],
              "path": ["auth", "refresh"]
            }
          },
          "event": [
            {
              "listen": "test",
              "script": {
                "type": "text/javascript",
                "exec": [
                  "pm.test('Status is 200', function () { pm.response.to.have.status(200); });",
                  "const json = pm.response.json();",
                  "if (json.accessToken) pm.collectionVariables.set('accessToken', json.accessToken);",
                  "if (json.refreshToken) pm.collectionVariables.set('refreshToken', json.refreshToken);"
                ]
              }
            }
          ]
        },
        {
          "name": "Logout",
          "request": {
            "method": "POST",
            "header": [
              { "key": "Content-Type", "value": "application/json" }
            ],
            "body": {
              "mode": "raw",
              "raw": "{\n  \"refreshToken\": \"{{refreshToken}}\",\n  \"accessToken\": \"{{accessToken}}\"\n}"
            },
            "url": {
              "raw": "{{baseUrl}}/auth/logout",
              "host": ["{{baseUrl}}"],
              "path": ["auth", "logout"]
            }
          }
        },
        {
          "name": "Password Reset Request",
          "request": {
            "method": "POST",
            "header": [
              { "key": "Content-Type", "value": "application/json" }
            ],
            "body": {
              "mode": "raw",
              "raw": "{\n  \"email\": \"{{email}}\"\n}"
            },
            "url": {
              "raw": "{{baseUrl}}/auth/password-reset",
              "host": ["{{baseUrl}}"],
              "path": ["auth", "password-reset"]
            }
          },
          "event": [
            {
              "listen": "test",
              "script": {
                "type": "text/javascript",
                "exec": [
                  "pm.test('Status is 200', function () { pm.response.to.have.status(200); });"
                ]
              }
            }
          ]
        },
        {
          "name": "Password Reset Confirm",
          "request": {
            "method": "POST",
            "header": [
              { "key": "Content-Type", "value": "application/json" }
            ],
            "body": {
              "mode": "raw",
              "raw": "{\n  \"token\": \"{{resetToken}}\",\n  \"newPassword\": \"{{newPassword}}\"\n}"
            },
            "url": {
              "raw": "{{baseUrl}}/auth/password-reset/confirm",
              "host": ["{{baseUrl}}"],
              "path": ["auth", "password-reset", "confirm"]
            }
          }
        }
      ]
    },
    {
      "name": "Utility",
      "item": [
        {
          "name": "JWKS",
          "request": {
            "method": "GET",
            "url": {
              "raw": "{{baseUrl}}/.well-known/jwks.json",
              "host": ["{{baseUrl}}"],
              "path": [".well-known", "jwks.json"]
            }
          }
        },
        {
          "name": "Actuator Health",
          "request": {
            "method": "GET",
            "url": {
              "raw": "{{baseUrl}}/actuator/health",
              "host": ["{{baseUrl}}"],
              "path": ["actuator", "health"]
            }
          }
        },
        {
          "name": "Actuator Info",
          "request": {
            "method": "GET",
            "url": {
              "raw": "{{baseUrl}}/actuator/info",
              "host": ["{{baseUrl}}"],
              "path": ["actuator", "info"]
            }
          }
        }
      ]
    }
  ]
}
